norsvinpy/__init__.py
norsvinpy/__main__.py
norsvinpy/functions.py
norsvinpy-0.1.3.dist-info/WHEEL
norsvinpy-0.1.3.dist-info/METADATA
norsvinpy-0.1.3.dist-info/RECORD
