Metadata-Version: 2.1
Name: norsvinpy
Version: 0.1.3
Summary: Python development in Norsvin
Author: Christopher
Author-email: christopher.coello@norsvin.no
Requires-Python: >=3.10,<3.12
Classifier: Programming Language :: Python :: 3
Classifier: Programming Language :: Python :: 3.10
Requires-Dist: numpy (>=1.23.3,<2.0.0)
Requires-Dist: requests (>=2.28.1,<3.0.0)
Requires-Dist: scipy (>=1.9.1,<2.0.0)
